saibr/__init__.py
saibr/legacy.py
saibr/misc.py
saibr/saibr.py
saibr-0.1.6.dist-info/LICENSE
saibr-0.1.6.dist-info/METADATA
saibr-0.1.6.dist-info/WHEEL
saibr-0.1.6.dist-info/top_level.txt
saibr-0.1.6.dist-info/RECORD
