Metadata-Version: 2.1
Name: saibr
Version: 0.1.6
Summary: Python implementation of SAIBR: a tool for performing spectral autofluorescence correction on biological images
Author-email: Tom Bland <tom_bland@hotmail.co.uk>
License: Attribution 4.0 International
Project-URL: Documentation, https://saibr.readthedocs.io/en/latest/
Project-URL: Source, https://github.com/goehringlab/saibr_python
License-File: LICENSE
Requires-Dist: numpy
Requires-Dist: matplotlib
Requires-Dist: scipy
Requires-Dist: ipywidgets
Requires-Dist: scikit-learn
Requires-Dist: scikit-image
Requires-Dist: jupyter
Requires-Dist: opencv-python
Provides-Extra: dev
Requires-Dist: pytest ; extra == 'dev'
Requires-Dist: pre-commit ; extra == 'dev'
Requires-Dist: black ; extra == 'dev'
Requires-Dist: pip-tools ; extra == 'dev'
Requires-Dist: pytest-cov ; extra == 'dev'
Provides-Extra: doc
Requires-Dist: sphinx-rtd-theme ==1.0.0 ; extra == 'doc'
